mxboard/__init__.py
mxboard/_crc32c.py
mxboard/event_file_writer.py
mxboard/record_writer.py
mxboard/summary.py
mxboard/utils.py
mxboard/writer.py
mxboard/proto/__init__.py
mxboard/proto/attr_value_pb2.py
mxboard/proto/event_pb2.py
mxboard/proto/graph_pb2.py
mxboard/proto/node_def_pb2.py
mxboard/proto/plugin_pr_curve_pb2.py
mxboard/proto/resource_handle_pb2.py
mxboard/proto/summary_pb2.py
mxboard/proto/tensor_pb2.py
mxboard/proto/tensor_shape_pb2.py
mxboard/proto/types_pb2.py
mxboard/proto/versions_pb2.py
mxboard-0.1.0.dist-info/DESCRIPTION.rst
mxboard-0.1.0.dist-info/METADATA
mxboard-0.1.0.dist-info/RECORD
mxboard-0.1.0.dist-info/WHEEL
mxboard-0.1.0.dist-info/metadata.json
mxboard-0.1.0.dist-info/top_level.txt
