Metadata-Version: 2.0
Name: mxboard
Version: 0.1.0
Summary: A logging tool for visualizing MXNet data in TensorBoard
Home-page: https://github.com/awslabs/mxboard
Author: Amazon Web Services
Author-email: jwum@amazon.com
License: Apache License 2.0
Keywords: mxnet tensor visualization machine deep learning
Platform: UNKNOWN
Classifier: Development Status :: 4 - Beta
Classifier: Intended Audience :: Developers
Classifier: Intended Audience :: Education
Classifier: Intended Audience :: Science/Research
Classifier: Topic :: Software Development :: Libraries :: Python Modules
Classifier: Topic :: Scientific/Engineering :: Mathematics
Classifier: Topic :: Software Development :: Libraries
Classifier: License :: OSI Approved :: Apache Software License
Classifier: Programming Language :: Python :: 2
Classifier: Programming Language :: Python :: 2.7
Classifier: Programming Language :: Python :: 3
Classifier: Programming Language :: Python :: 3.5
Classifier: Programming Language :: Python :: 3.6
Requires-Dist: numpy
Requires-Dist: protobuf (>=3.0.0)
Requires-Dist: Pillow
Requires-Dist: six
